PDS_TPF/hdl/modfs4.vhd
----------------------------------------------------------------------------------
-- Company: 
-- Engineer: 
-- 
-- Create Date: 11.12.2023 04:12:18
-- Design Name: 
-- Module Name: modFS4 - Behavioral
-- Project Name: 
-- Target Devices: 
-- Tool Versions: 
-- Description: 
-- 
-- Dependencies: 
-- 
-- Revision:
-- Revision 0.01 - File Created
-- Additional Comments:
-- 
----------------------------------------------------------------------------------


library IEEE;
use IEEE.STD_LOGIC_1164.ALL;
use ieee.numeric_std.all;

-- Uncomment the following library declaration if using
-- arithmetic functions with Signed or Unsigned values
--use IEEE.NUMERIC_STD.ALL;

-- Uncomment the following library declaration if instantiating
-- any Xilinx leaf cells in this code.
--library UNISIM;
--use UNISIM.VComponents.all;

entity modfs4 is
	generic (
          DATA_IN_WIDTH     : integer := 16;
          DATA_OUT_WIDTH    : integer := 16
	);
	  
    Port ( 	clk_i 	: IN std_logic;
			reset_i: IN std_logic;
			data_i 	: in STD_LOGIC_VECTOR (127 downto 0);
			data_q 	: in STD_LOGIC_VECTOR (127 downto 0);
			out_in 	: out STD_LOGIC_VECTOR (127 downto 0);
			out_qn 	: out STD_LOGIC_VECTOR (127 downto 0));
end modfs4;

architecture Behavioral of modfs4 is
signal out_i1, out_i2, out_i3, out_i4, out_i5, out_i6, out_i7, out_i8 : std_logic_vector(DATA_OUT_WIDTH-1 downto 0) := (others => '0');
signal out_q1, out_q2, out_q3, out_q4, out_q5, out_q6, out_q7, out_q8 : std_logic_vector(DATA_OUT_WIDTH-1 downto 0) := (others => '0');



signal bufa : signed(15 downto 0);
begin
	process(clk_i, reset_i)
	begin
		if reset_i = '1' then 
            out_in <= (others => '0');
            out_qn <= (others => '0');
		elsif rising_edge(clk_i) then
		

			-- 0 GRADOS
            -- out_i1 <= std_logic_vector(to_signed( (to_integer(signed(sample_i1)) * 1 - to_integer(signed(sample_q1)) * 0) , DATA_IN_WIDTH ));
            -- out_q1 <= std_logic_vector(to_signed( (to_integer(signed(sample_i1)) * 0 + to_integer(signed(sample_q1)) * 1) , DATA_IN_WIDTH ));
            out_i1 <= std_logic_vector(to_signed(to_integer(signed(data_i(127 downto 112))), DATA_IN_WIDTH));
            out_q1 <= std_logic_vector(to_signed(to_integer(signed(data_q(127 downto 112))), DATA_IN_WIDTH));
			
			-- pi/2
            -- out_i2 <= std_logic_vector(to_signed( (to_integer(signed(sample_i1)) * 0 - to_integer(signed(sample_q1)) * 1) , DATA_IN_WIDTH ));
            -- out_q2 <= std_logic_vector(to_signed( (to_integer(signed(sample_i1)) * 1 + to_integer(signed(sample_q1)) * 0) , DATA_IN_WIDTH ));
            out_i2 <= std_logic_vector(to_signed( to_integer(signed(data_q ( 111 downto 96))) * to_integer(to_signed(-1,DATA_IN_WIDTH)), DATA_IN_WIDTH ));
            out_q2 <= std_logic_vector(to_signed( to_integer(signed(data_i ( 111 downto 96))) , DATA_IN_WIDTH ));
			
			-- pi
            -- out_i3 <= std_logic_vector(to_signed( (to_integer(signed(sample_i1)) * -1 - to_integer(signed(sample_q1)) * 0) , DATA_IN_WIDTH ));
            -- out_q3 <= std_logic_vector(to_signed( (to_integer(signed(sample_i1)) * 0 + to_integer(signed(sample_q1)) * -1) , DATA_IN_WIDTH ));
            out_i3 <= std_logic_vector(to_signed( to_integer(signed(data_i ( 95 downto 80))) *  to_integer(to_signed(-1,DATA_IN_WIDTH)) , DATA_IN_WIDTH ));
            out_q3 <= std_logic_vector(to_signed( to_integer(signed(data_q ( 95 downto 80))) *  to_integer(to_signed(-1,DATA_IN_WIDTH)) , DATA_IN_WIDTH ));
			
			-- 3pi/2
            -- out_i4 <= std_logic_vector(to_signed( (to_integer(signed(sample_i1)) * 0 - to_integer(signed(sample_q1)) * -1) , DATA_IN_WIDTH ));
            -- out_q4 <= std_logic_vector(to_signed( (to_integer(signed(sample_i1)) * -1 + to_integer(signed(sample_q1)) * 0) , DATA_IN_WIDTH ));
            out_i4 <= std_logic_vector(to_signed( to_integer(signed(data_q ( 79 downto 64))) , DATA_IN_WIDTH ));
            out_q4 <= std_logic_vector(to_signed( to_integer(signed(data_i ( 79 downto 64))) *  to_integer(to_signed(-1,DATA_IN_WIDTH))  , DATA_IN_WIDTH ));
			
            out_i5 <= std_logic_vector(to_signed( to_integer(signed(data_i ( 63 downto 48))) , DATA_IN_WIDTH ));
            out_q5 <= std_logic_vector(to_signed( to_integer(signed(data_q ( 63 downto 48))) , DATA_IN_WIDTH ));
            out_i6 <= std_logic_vector(to_signed( to_integer(signed(data_q ( 47 downto 32))) * to_integer(to_signed(-1,DATA_IN_WIDTH)), DATA_IN_WIDTH ));
            out_q6 <= std_logic_vector(to_signed( to_integer(signed(data_i ( 47 downto 32))) , DATA_IN_WIDTH ));
            out_i7 <= std_logic_vector(to_signed( to_integer(signed(data_i ( 31 downto 16))) *  to_integer(to_signed(-1,DATA_IN_WIDTH)) , DATA_IN_WIDTH ));
            out_q7 <= std_logic_vector(to_signed( to_integer(signed(data_q ( 31 downto 16))) *  to_integer(to_signed(-1,DATA_IN_WIDTH)) , DATA_IN_WIDTH ));
            out_i8 <= std_logic_vector(to_signed( to_integer(signed(data_q ( 15 downto 0))) , DATA_IN_WIDTH ));
            out_q8 <= std_logic_vector(to_signed( to_integer(signed(data_i ( 15 downto 0))) *  to_integer(to_signed(-1,DATA_IN_WIDTH))  , DATA_IN_WIDTH ));
			
	        -- out_in(127 downto 112) 	<= out_i1 ;
            out_in <= out_i1 & out_i2 & out_i3 & out_i4 & out_i5 & out_i6 & out_i7 & out_i8;
            out_qn <= out_q1 & out_q2 & out_q3 & out_q4 & out_q5 & out_q6 & out_q7 & out_q8;
		end if;
		
	end process;
	-- out_in(127 downto 112) 	<= out_i1 ;
	--out_in(111 downto 95) 	<= out_i2 ;
	--out_in(95 downto 80) 	<= out_i3 ;
	--out_in(79 downto 64) 	<= out_i4 ;
	--out_in(63 downto 48) 	<= out_i5 ;
	--out_in(47 downto 32) 	<= out_i5 ;
	--out_in(31 downto 16) 	<= out_i6 ;
	--out_in(15 downto 0) 	<= out_i7 ;
	
	--out_in <= out_i1 & out_i2 & out_i3 & out_i4 & out_i5 & out_i6 & out_i7 & out_i8;
	--out_qn <= out_q1 & out_q2 & out_q3 & out_q4 & out_q5 & out_q6 & out_q7 & out_q8;

end architecture Behavioral;

PDS_TPF/tests/waveforms/modFS4.vcd
$date
  Mon Dec 11 15:25:30 2023
$end
$version
  GHDL v0
$end
$timescale
  1 fs
$end
$scope module standard $end
$upscope $end
$scope module std_logic_1164 $end
$upscope $end
$scope module numeric_std $end
$upscope $end
$scope module modfs4 $end
$var reg 1 ! clk_i $end
$var reg 1 " reset_i $end
$var reg 128 # data_i[127:0] $end
$var reg 128 $ data_q[127:0] $end
$var reg 128 % out_in[127:0] $end
$var reg 128 & out_qn[127:0] $end
$var reg 16 ' out_i1[15:0] $end
$var reg 16 ( out_i2[15:0] $end
$var reg 16 ) out_i3[15:0] $end
$var reg 16 * out_i4[15:0] $end
$var reg 16 + out_i5[15:0] $end
$var reg 16 , out_i6[15:0] $end
$var reg 16 - out_i7[15:0] $end
$var reg 16 . out_i8[15:0] $end
$var reg 16 / out_q1[15:0] $end
$var reg 16 0 out_q2[15:0] $end
$var reg 16 1 out_q3[15:0] $end
$var reg 16 2 out_q4[15:0] $end
$var reg 16 3 out_q5[15:0] $end
$var reg 16 4 out_q6[15:0] $end
$var reg 16 5 out_q7[15:0] $end
$var reg 16 6 out_q8[15:0] $end
$var reg 16 7 bufa[15:0] $end
$upscope $end
$enddefinitions $end
#0
1!
1"
b00000000000000000000000000000000000000000000000000000000000000000000000000000000000000000000000000000000000000000000000000000000 #
b00000000000000000000000000000000000000000000000000000000000000000000000000000000000000000000000000000000000000000000000000000000 $
b00000000000000000000000000000000000000000000000000000000000000000000000000000000000000000000000000000000000000000000000000000000 %
b00000000000000000000000000000000000000000000000000000000000000000000000000000000000000000000000000000000000000000000000000000000 &
b0000000000000000 '
b0000000000000000 (
b0000000000000000 )
b0000000000000000 *
b0000000000000000 +
b0000000000000000 ,
b0000000000000000 -
b0000000000000000 .
b0000000000000000 /
b0000000000000000 0
b0000000000000000 1
b0000000000000000 2
b0000000000000000 3
b0000000000000000 4
b0000000000000000 5
b0000000000000000 6
bUUUUUUUUUUUUUUUU 7
#1000000
0!
#2000000
1!
#3000000
0!
#4000000
1!
#5000000
0!
0"
b01111111111111110101110101001110000010000000100110101110011010011000000100000100100110000111010111101000000001110100010010011000 #
b00000000000000000101011110011110011111111011111001100010100111100001000000001001101101001100001110000010010001011001001111110001 $
#6000000
1!
b01011101010011100000100000001001101011100110100110000001000001001001100001110101111010000000011101000100100110000111101111111010 #
b01010111100111100111111110111110011000101001111000010000000010011011010011000011100000100100010110010011111100011110000000110001 $
b0101110101001110 '
b1000000001000010 (
b0101000110010111 )
b0001000000001001 *
b1001100001110101 +
b0111110110111011 ,
b1011101101101000 -
b1110000000110001 .
b0101011110011110 /
b0000100000001001 0
b1001110101100010 1
b0111111011111100 2
b1011010011000011 3
b1110100000000111 4
b0110110000001111 5
b1000010000000110 6
#7000000
0!
b00001000000010011010111001101001100000010000010010011000011101011110100000000111010001001001100001111011111110100111000000100110 #
b01111111101111100110001010011110000100000000100110110100110000111000001001000101100100111111000111100000001100010011110110101111 $
#8000000
1!
b10101110011010011000000100000100100110000111010111101000000001110100010010011000011110111111101001110000001001100010011110000101 #
b01100010100111100001000000001001101101001100001110000010010001011001001111110001111000000011000100111101101011110111100110111101 $
b01011101010011101000000001000010010100011001011100010000000010011001100001110101011111011011101110111011011010001110000000110001 %
b01010111100111100000100000001001100111010110001001111110111111001011010011000011111010000000011101101100000011111000010000000110 &
b1010111001101001 '
b1110111111110111 (
b0110011110001011 )
b1000001001000101 *
b0100010010011000 +
b0001111111001111 ,
b1000111111011010 -
b0111100110111101 .
b0110001010011110 /
b1000000100000100 0
b0100101100111101 1
b0001011111111001 2
b1001001111110001 3
b0111101111111010 4
b1100001001010001 5
b1101100001111011 6
#9000000
0!
b10000001000001001001100001110101111010000000011101000100100110000111101111111010011100000010011000100111100001011100100101111000 #
b00010000000010011011010011000011100000100100010110010011111100011110000000110001001111011010111101111001101111010111001111001100 $
#10000000
1!
b10011000011101011110100000000111010001001001100001111011111110100111000000100110001001111000010111001001011110001000100011111010 #
b10110100110000111000001001000101100100111111000111100000001100010011110110101111011110011011110101110011110011000010111100010011 $
b10101110011010011110111111110111011001111000101110000010010001010100010010011000000111111100111110001111110110100111100110111101 %
b01100010100111101000000100000100010010110011110100010111111110011001001111110001011110111111101011000010010100011101100001111011 &
b1001100001110101 '
b0111110110111011 (
b1011101101101000 )
b1110000000110001 *
b0111000000100110 +
b1000011001000011 ,
b0011011010001000 -
b0010111100010011 .
b1011010011000011 /
b1110100000000111 0
b0110110000001111 1
b1000010000000110 2
b0011110110101111 3
b0010011110000101 4
b1000110000110100 5
b0111011100000110 6
#11000000
0!
b11101000000001110100010010011000011110111111101001110000001001100010011110000101110010010111100010001000111110101000100100000100 #
b10000010010001011001001111110001111000000011000100111101101011110111100110111101011100111100110000101111000100111101000011010101 $
#12000000
1!
b01000100100110000111101111111010011100000010011000100111100001011100100101111000100010001111101010001001000001001100100110010000 #
b10010011111100011110000000110001001111011010111101111001101111010111001111001100001011110001001111010000110101011000110000101001 $
b10011000011101010111110110111011101110110110100011100000001100010111000000100110100001100100001100110110100010000010111100010011 %
b10110100110000111110100000000111011011000000111110000100000001100011110110101111001001111000010110001100001101000111011100000110 &
b0100010010011000 '
b0001111111001111 (
b1000111111011010 )
b0111100110111101 *
b1100100101111000 +
b1101000011101101 ,
b0111011011111100 -
b1000110000101001 .
b1001001111110001 /
b0111101111111010 0
b1100001001010001 1
b1101100001111011 2
b0111001111001100 3
b1000100011111010 4
b0010111100101011 5
b0011011001110000 6
#13000000
0!
b01111011111110100111000000100110001001111000010111001001011110001000100011111010100010010000010011001001100100000010011110011111 #
b11100000001100010011110110101111011110011011110101110011110011000010111100010011110100001101010110001100001010011000011001001011 $
#14000000
1!
b01110000001001100010011110000101110010010111100010001000111110101000100100000100110010011001000000100111100111110111000000110100 #
b00111101101011110111100110111101011100111100110000101111000100111101000011010101100011000010100110000110010010111100001001101001 $
b01000100100110000001111111001111100011111101101001111001101111011100100101111000110100001110110101110110111111001000110000101001 %
b10010011111100010111101111111010110000100101000111011000011110110111001111001100100010001111101000101111001010110011011001110000 &
b0111000000100110 '
b1000011001000011 (
b0011011010001000 )
b0010111100010011 *
b1000100100000100 +
b0111001111010111 ,
b1101100001100001 -
b1100001001101001 .
b0011110110101111 /
b0010011110000101 0
b1000110000110100 1
b0111011100000110 2
b1101000011010101 3
b1100100110010000 4
b0111100110110101 5
b1000111111001100 6
#15000000
0!
b00100111100001011100100101111000100010001111101010001001000001001100100110010000001001111001111101110000001101000111101111110011 #
b01111001101111010111001111001100001011110001001111010000110101011000110000101001100001100100101111000010011010010001111111101011 $
#16000000
1!
b11001001011110001000100011111010100010010000010011001001100100000010011110011111011100000011010001111011111100110100010001111110 #
b01110011110011000010111100010011110100001101010110001100001010011000011001001011110000100110100100011111111010110110110000100000 $
b01110000001001101000011001000011001101101000100000101111000100111000100100000100011100111101011111011000011000011100001001101001 %
b00111101101011110010011110000101100011000011010001110111000001101101000011010101110010011001000001111001101101011000111111001100 &
b1100100101111000 '
b1101000011101101 (
b0111011011111100 )
b1000110000101001 *
b0010011110011111 +
b0011110110010111 ,
b1000010000001101 -
b0110110000100000 .
b0111001111001100 /
b1000100011111010 0
b0010111100101011 1
b0011011001110000 2
b1000011001001011 3
b0111000000110100 4
b1110000000010101 5
b1011101110000010 6
#17000000
0!
b10001000111110101000100100000100110010011001000000100111100111110111000000110100011110111111001101000100011111101110011111100111 #
b00101111000100111101000011010101100011000010100110000110010010111100001001101001000111111110101101101100001000000111110110110101 $
#18000000
1!
b10001001000001001100100110010000001001111001111101110000001101000111101111110011010001000111111011100111111001111001100001100000 #
b11010000110101011000110000101001100001100100101111000010011010010001111111101011011011000010000001111101101101010100101100100001 $
b11001001011110001101000011101101011101101111110010001100001010010010011110011111001111011001011110000100000011010110110000100000 %
b01110011110011001000100011111010001011110010101100110110011100001000011001001011011100000011010011100000000101011011101110000010 &
b1000100100000100 '
b0111001111010111 (
b1101100001100001 )
b1100001001101001 *
b0111101111110011 +
b1001001111100000 ,
b0001100000011001 -
b0100101100100001 .
b1101000011010101 /
b1100100110010000 0
b0111100110110101 1
b1000111111001100 2
b0001111111101011 3
b0100010001111110 4
b1000001001001011 5
b0110011110100000 6
#19000000
0!
b11001001100100000010011110011111011100000011010001111011111100110100010001111110111001111110011110011000011000001000000100001000 #
b10001100001010011000011001001011110000100110100100011111111010110110110000100000011111011011010101001011001000011110111111010010 $
#20000000
1!
b00100111100111110111000000110100011110111111001101000100011111101110011111100111100110000110000010000001000010001010111010001001 #
b10000110010010111100001001101001000111111110101101101100001000000111110110110101010010110010000111101111110100101001110101001000 $
b10001001000001000111001111010111110110000110000111000010011010010111101111110011100100111110000000011000000110010100101100100001 %
b11010000110101011100100110010000011110011011010110001111110011000001111111101011010001000111111010000010010010110110011110100000 &
b0010011110011111 '
b0011110110010111 (
b1000010000001101 )
b0110110000100000 *
b1110011111100111 +
b1011010011011111 ,
b0111111011111000 -
b1001110101001000 .
b1000011001001011 /
b0111000000110100 0
b1110000000010101 1
b1011101110000010 2
b0111110110110101 3
b1001100001100000 4
b0001000000101110 5
b0101000101110111 6
#21000000
0!
b01110000001101000111101111110011010001000111111011100111111001111001100001100000100000010000100010101110100010010000100000110100 #
b11000010011010010001111111101011011011000010000001111101101101010100101100100001111011111101001010011101010010001000000001000101 $
#22000000
1!
b01111011111100110100010001111110111001111110011110011000011000001000000100001000101011101000100100001000001101000101110101101110 #
b00011111111010110110110000100000011111011011010101001011001000011110111111010010100111010100100010000000010001011010100010000101 $
b00100111100111110011110110010111100001000000110101101100001000001110011111100111101101001101111101111110111110001001110101001000 %
b10000110010010110111000000110100111000000001010110111011100000100111110110110101100110000110000000010000001011100101000101110111 &
b0111101111110011 '
b1001001111100000 (
b0001100000011001 )
b0100101100100001 *
b1000000100001000 +
b0110001010111000 ,
b1111011111001100 -
b1010100010000101 .
b0001111111101011 /
b0100010001111110 0
b1000001001001011 1
b0110011110100000 2
b1110111111010010 3
b1010111010001001 4
b0111111110111011 5
b1010001010010010 6
#23000000
0!
b01000100011111101110011111100111100110000110000010000001000010001010111010001001000010000011010001011101011011100111111111111110 #
b01101100001000000111110110110101010010110010000111101111110100101001110101001000100000000100010110101000100001010000000000110011 $
#24000000
1!
b11100111111001111001100001100000100000010000100010101110100010010000100000110100010111010110111001111111111111100101110100100111 #
b01111101101101010100101100100001111011111101001010011101010010001000000001000101101010001000010100000000001100110101011111000111 $
b01111011111100111001001111100000000110000001100101001011001000011000000100001000011000101011100011110111110011001010100010000101 %
b00011111111010110100010001111110100000100100101101100111101000001110111111010010101011101000100101111111101110111010001010010010 &
b1110011111100111 '
b1011010011011111 (
b0111111011111000 )
b1001110101001000 *
b0000100000110100 +
b0101011101111011 ,
b1000000000000010 -
b0101011111000111 .
b0111110110110101 /
b1001100001100000 0
b0001000000101110 1
b0101000101110111 2
b1000000001000101 3
b0101110101101110 4
b1111111111001101 5
b1010001011011001 6
#25000000
0!
b10011000011000001000000100001000101011101000100100001000001101000101110101101110011111111111111001011101001001110000011111001101 #
b01001011001000011110111111010010100111010100100010000000010001011010100010000101000000000011001101010111110001110111111111000010 $
#26000000
1!
b10000001000010001010111010001001000010000011010001011101011011100111111111111110010111010010011100000111110011011010111000111000 #
b11101111110100101001110101001000100000000100010110101000100001010000000000110011010101111100011101111111110000100110001001110110 $
b11100111111001111011010011011111011111101111100010011101010010000000100000110100010101110111101110000000000000100101011111000111 %
b01111101101101011001100001100000000100000010111001010001011101111000000001000101010111010110111011111111110011011010001011011001 &
b1000000100001000 '
b0110001010111000 (
b1111011111001100 )
b1010100010000101 *
b0111111111111110 +
b1010100000111001 ,
b1111100000110011 -
b0110001001110110 .
b1110111111010010 /
b1010111010001001 0
b0111111110111011 1
b1010001010010010 2
b0000000000110011 3
b0101110100100111 4
b1000000000111110 5
b0101000111001000 6
#27000000
0!
b10101110100010010000100000110100010111010110111001111111111111100101110100100111000001111100110110101110001110001000000011111011 #
b10011101010010001000000001000101101010001000010100000000001100110101011111000111011111111100001001100010011101100000111111000110 $
#28000000
1!
b00001000001101000101110101101110011111111111111001011101001001110000011111001101101011100011100010000000111110111001100010011111 #
b10000000010001011010100010000101000000000011001101010111110001110111111111000010011000100111011000001111110001101011010010001001 $
b10000001000010000110001010111000111101111100110010101000100001010111111111111110101010000011100111111000001100110110001001110110 %
b11101111110100101010111010001001011111111011101110100010100100100000000000110011010111010010011110000000001111100101000111001000 &
b0000100000110100 '
b0101011101111011 (
b1000000000000010 )
b0101011111000111 *
b0000011111001101 +
b1001110110001010 ,
b0111111100000101 -
b1011010010001001 .
b1000000001000101 /
b0101110101101110 0
b1111111111001101 1
b1010001011011001 2
b0111111111000010 3
b1010111000111000 4
b1111000000111010 5
b0110011101100001 6
#29000000
0!
b01011101011011100111111111111110010111010010011100000111110011011010111000111000100000001111101110011000100111111110100001010010 #
b10101000100001010000000000110011010101111100011101111111110000100110001001110110000011111100011010110100100010011000001000110111 $
#30000000
1!
b01111111111111100101110100100111000001111100110110101110001110001000000011111011100110001001111111101000010100100100010011011100 #
b00000000001100110101011111000111011111111100001001100010011101100000111111000110101101001000100110000010001101111001010000011100 $
b00001000001101000101011101111011100000000000001001010111110001110000011111001101100111011000101001111111000001011011010010001001 %
b10000000010001010101110101101110111111111100110110100010110110010111111111000010101011100011100011110000001110100110011101100001 &
b0111111111111110 '
b1010100000111001 (
b1111100000110011 )
b0110001001110110 *
b1000000011111011 +
b0100101101110111 ,
b0001011110101110 -
b1001010000011100 .
b0000000000110011 /
b0101110100100111 0
b1000000000111110 1
b0101000111001000 2
b0000111111000110 3
b1001100010011111 4
b0111110111001001 5
b1011101100100100 6
#31000000
0!
b01011101001001110000011111001101101011100011100010000000111110111001100010011111111010000101001001000100110111000111110000001111 #
b01010111110001110111111111000010011000100111011000001111110001101011010010001001100000100011011110010100000111001110000010000011 $
#32000000
1!
b00000111110011011010111000111000100000001111101110011000100111111110100001010010010001001101110001111100000011110110111111111011 #
b01111111110000100110001001110110000011111100011010110100100010011000001000110111100101000001110011100000100000110011110111111100 $
b01111111111111101010100000111001111110000011001101100010011101101000000011111011010010110111011100010111101011101001010000011100 %
b00000000001100110101110100100111100000000011111001010001110010000000111111000110100110001001111101111101110010011011101100100100 &
b0000011111001101 '
b1001110110001010 (
b0111111100000101 )
b1011010010001001 *
b1110100001010010 +
b0110101111100100 ,
b1000001111110001 -
b0011110111111100 .
b0111111111000010 /
b1010111000111000 0
b1111000000111010 1
b0110011101100001 2
b1000001000110111 3
b0100010011011100 4
b0001111101111101 5
b1001000000000101 6
#33000000
0!
b10101110001110001000000011111011100110001001111111101000010100100100010011011100011111000000111101101111111110110010011100101101 #
b01100010011101100000111111000110101101001000100110000010001101111001010000011100111000001000001100111101111111000111100111011010 $
#34000000
1!
b10000000111110111001100010011111111010000101001001000100110111000111110000001111011011111111101100100111001011011100100100100000 #
b00001111110001101011010010001001100000100011011110010100000111001110000010000011001111011111110001111001110110100111001110100010 $
b00000111110011011001110110001010011111110000010110110100100010011110100001010010011010111110010010000011111100010011110111111100 %
b01111111110000101010111000111000111100000011101001100111011000011000001000110111010001001101110000011111011111011001000000000101 &
b1000000011111011 '
b0100101101110111 (
b0001011110101110 )
b1001010000011100 *
b0111110000001111 +
b1100001000000100 ,
b1101100011010011 -
b0111001110100010 .
b0000111111000110 /
b1001100010011111 0
b0111110111001001 1
b1011101100100100 2
b1110000010000011 3
b0110111111111011 4
b1000011000100110 5
b0011011011100000 6
#35000000
0!
b10011000100111111110100001010010010001001101110001111100000011110110111111111011001001110010110111001001001000001000100011010101 #
b10110100100010011000001000110111100101000001110011100000100000110011110111111100011110011101101001110011101000100010111010110101 $
#36000000
1!
b11101000010100100100010011011100011111000000111101101111111110110010011100101101110010010010000010001000110101011000100100101010 #
b10000010001101111001010000011100111000001000001100111101111111000111100111011010011100111010001000101110101101011101000001110100 $
b10000000111110110100101101110111000101111010111010010100000111000111110000001111110000100000010011011000110100110111001110100010 %
b00001111110001101001100010011111011111011100100110111011001001001110000010000011011011111111101110000110001001100011011011100000 &
b1110100001010010 '
b0110101111100100 (
b1000001111110001 )
b0011110111111100 *
b0010011100101101 +
b1000110001011110 ,
b0111011100101011 -
b1101000001110100 .
b1000001000110111 /
b0100010011011100 0
b0001111101111101 1
b1001000000000101 2
b0111100111011010 3
b1100100100100000 4
b1101000101001011 5
b0111011011010110 6
#37000000
0!
b01000100110111000111110000001111011011111111101100100111001011011100100100100000100010001101010110001001001010101100100111110010 #
b10010100000111001110000010000011001111011111110001111001110110100111001110100010001011101011010111010000011101001000101111111011 $
#38000000
1!
b01111100000011110110111111111011001001110010110111001001001000001000100011010101100010010010101011001001111100100010100000001010 #
b11100000100000110011110111111100011110011101101001110011101000100010111010110101110100000111010010001011111110111000011001101110 $
b11101000010100100110101111100100100000111111000100111101111111000010011100101101100011000101111001110111001010111101000001110100 %
b10000010001101110100010011011100000111110111110110010000000001010111100111011010110010010010000011010001010010110111011011010110 &
b0111110000001111 '
b1100001000000100 (
b1101100011010011 )
b0111001110100010 *
b1000100011010101 +
b0010111110001100 ,
b0011011000001110 -
b1000011001101110 .
b1110000010000011 /
b0110111111111011 0
b1000011000100110 1
b0011011011100000 2
b0010111010110101 3
b1000100100101010 4
b0111010000000101 5
b1101011111110110 6
#39000000
0!
b01101111111110110010011100101101110010010010000010001000110101011000100100101010110010011111001000101000000010100111000001101100 #
b00111101111111000111100111011010011100111010001000101110101101011101000001110100100010111111101110000110011011101100001011010000 $
#40000000
1!
b00100111001011011100100100100000100010001101010110001001001010101100100111110010001010000000101001110000011011000111101111010101 #
b01111001110110100111001110100010001011101011010111010000011101001000101111111011100001100110111011000010110100000010000001100001 $
b01111100000011111100001000000100110110001101001101110011101000101000100011010101001011111000110000110110000011101000011001101110 %
b11100000100000110110111111111011100001100010011000110110111000000010111010110101100010010010101001110100000001011101011111110110 &
b0010011100101101 '
b1000110001011110 (
b0111011100101011 )
b1101000001110100 *
b1100100111110010 +
b0111100110010010 ,
b1000111110010100 -
b0010000001100001 .
b0111100111011010 /
b1100100100100000 0
b1101000101001011 1
b0111011011010110 2
b1000101111111011 3
b0010100000001010 4
b0011110100110000 5
b1000010000101011 6
#41000000
0!
b11001001001000001000100011010101100010010010101011001001111100100010100000001010011100000110110001111011110101010100010000010100 #
b01110011101000100010111010110101110100000111010010001011111110111000011001101110110000101101000000100000011000010110110001100011 $
#42000000
1!
b10001000110101011000100100101010110010011111001000101000000010100111000001101100011110111101010101000100000101001110011101101000 #
b00101110101101011101000001110100100010111111101110000110011011101100001011010000001000000110000101101100011000110111110110011100 $
b00100111001011011000110001011110011101110010101111010000011101001100100111110010011110011001001010001111100101000010000001100001 %
b01111001110110101100100100100000110100010100101101110110110101101000101111111011001010000000101000111101001100001000010000101011 &
b1000100011010101 '
b0010111110001100 (
b0011011000001110 )
b1000011001101110 *
b0111000001101100 +
b1101111110011111 ,
b1011101111101100 -
b0111110110011100 .
b0010111010110101 /
b1000100100101010 0
b0111010000000101 1
b1101011111110110 2
b1100001011010000 3
b0111101111010101 4
b1001001110011101 5
b0001100010011000 6
#43000000
0!
b10001001001010101100100111110010001010000000101001110000011011000111101111010101010001000001010011100111011010001001100000010010 #
b11010000011101001000101111111011100001100110111011000010110100000010000001100001011011000110001101111101100111000100101010110100 $
#44000000
1!
b11001001111100100010100000001010011100000110110001111011110101010100010000010100111001110110100010011000000100101000000100011010 #
b10001011111110111000011001101110110000101101000000100000011000010110110001100011011111011001110001001010101101001110111101001001 $
b10001000110101010010111110001100001101100000111010000110011011100111000001101100110111111001111110111011111011000111110110011100 %
b00101110101101011000100100101010011101000000010111010111111101101100001011010000011110111101010110010011100111010001100010011000 &
b1100100111110010 '
b0111100110010010 (
b1000111110010100 )
b0010000001100001 *
b0100010000010100 +
b1000001001100100 ,
b0110011111101110 -
b1110111101001001 .
b1000101111111011 /
b0010100000001010 0
b0011110100110000 1
b1000010000101011 2
b0110110001100011 3
b1110011101101000 4
b1011010101001100 5
b0111111011100110 6
#45000000
0!
b00101000000010100111000001101100011110111101010101000100000101001110011101101000100110000001001010000001000110101010111011110111 #
b10000110011011101100001011010000001000000110000101101100011000110111110110011100010010101011010011101111010010011001110011101110 $
#46000000
1!
b01110000011011000111101111010101010001000001010011100111011010001001100000010010100000010001101010101110111101110000100011000110 #
b11000010110100000010000001100001011011000110001101111101100111000100101010110100111011110100100110011100111011101000000001001111 $
b11001001111100100111100110010010100011111001010000100000011000010100010000010100100000100110010001100111111011101110111101001001 %
b10001011111110110010100000001010001111010011000010000100001010110110110001100011111001110110100010110101010011000111111011100110 &
b0111000001101100 '
b1101111110011111 (
b1011101111101100 )
b0111110110011100 *
b1001100000010010 +
b0001000010110111 ,
b0101000100001001 -
b1000000001001111 .
b1100001011010000 /
b0111101111010101 0
b1001001110011101 1
b0001100010011000 2
b0100101010110100 3
b1000000100011010 4
b0110001100010010 5
b1111011100111010 6
#47000000
0!
b01111011110101010100010000010100111001110110100010011000000100101000000100011010101011101111011100001000110001100101110111010101 #
b00100000011000010110110001100011011111011001110001001010101101001110111101001001100111001110111010000000010011111010100011110010 $
#48000000
1!
b01000100000101001110011101101000100110000001001010000001000110101010111011110111000010001100011001011101110101010111111111111110 #
b01101100011000110111110110011100010010101011010011101111010010011001110011101110100000000100111110101000111100100000000011001101 $
b01110000011011001101111110011111101110111110110001111101100111001001100000010010000100001011011101010001000010011000000001001111 %
b11000010110100000111101111010101100100111001110100011000100110000100101010110100100000010001101001100011000100101111011100111010 &
b0100010000010100 '
b1000001001100100 (
b0110011111101110 )
b1110111101001001 *
b1010111011110111 +
b0111111110110001 ,
b1010001000101011 -
b0000000011001101 .
b0110110001100011 /
b1110011101101000 0
b1011010101001100 1
b0111111011100110 2
b1001110011101110 3
b0000100011000110 4
b0101011100001110 5
b1000000000000010 6
#49000000
0!
b11100111011010001001100000010010100000010001101010101110111101110000100011000110010111011101010101111111111111100101110010111010 #
b01111101100111000100101010110100111011110100100110011100111011101000000001001111101010001111001000000000110011010101100000111010 $
#50000000
1!
b10011000000100101000000100011010101011101111011100001000110001100101110111010101011111111111111001011100101110100000011100101011 #
b01001010101101001110111101001001100111001110111010000000010011111010100011110010000000001100110101011000001110100111111111001011 $
b01000100000101001000001001100100011001111110111011101111010010011010111011110111011111111011000110100010001010110000000011001101 %
b01101100011000111110011101101000101101010100110001111110111001101001110011101110000010001100011001010111000011101000000000000010 &
b1001100000010010 '
b0001000010110111 (
b0101000100001001 )
b1000000001001111 *
b0101110111010101 +
b1111111100110011 ,
b1010001101000110 -
b0111111111001011 .
b0100101010110100 /
b1000000100011010 0
b0110001100010010 1
b1111011100111010 2
b1010100011110010 3
b0111111111111110 4
b1010011111000110 5
b1111100011010101 6
#51000000
0!
b10000001000110101010111011110111000010001100011001011101110101010111111111111110010111001011101000000111001010111010110110111000 #
b11101111010010011001110011101110100000000100111110101000111100100000000011001101010110000011101001111111110010110110001000001011 $
